tessti/__init__.py
tessti/cli.py
tessti/config.py
tessti/hpc.py
tessti/main.py
tessti/scheduler.py
tessti-0.1.1.dist-info/METADATA
tessti-0.1.1.dist-info/WHEEL
tessti-0.1.1.dist-info/entry_points.txt
tessti-0.1.1.dist-info/top_level.txt
tessti-0.1.1.dist-info/RECORD
