Metadata-Version: 2.1
Name: tessti
Version: 0.1.1
Summary: A tool to schedule SLURM jobs made as simple as possible.
Home-page: https://github.com/ListIndexOutOfRange/tessti
Author: Luc Vedrenne
Author-email: vedrenneluc@gmail.com
License: GPLv3
Classifier: Development Status :: 3 - Alpha
Classifier: Intended Audience :: Developers
Classifier: Intended Audience :: Science/Research
Classifier: Intended Audience :: Education
Classifier: License :: OSI Approved :: GNU General Public License v3 (GPLv3)
Classifier: Natural Language :: English
Classifier: Programming Language :: Python :: 3
Requires-Python: >=3.7
Requires-Dist: fire
Requires-Dist: prettytable
Requires-Dist: toml
